foliconf/__init__.py
foliconf/__main__.py
foliconf-0.2.dist-info/LICENSE
foliconf-0.2.dist-info/METADATA
foliconf-0.2.dist-info/WHEEL
foliconf-0.2.dist-info/top_level.txt
foliconf-0.2.dist-info/RECORD
