Metadata-Version: 2.1
Name: foliconf
Version: 0.2
Author-email: Emmanuel Bengio <bengioe@gmail.com>
Keywords: foliconf
Classifier: Operating System :: OS Independent
Classifier: Programming Language :: Python
Classifier: Programming Language :: Python :: 3
Requires-Python: >=3.8
License-File: LICENSE
Requires-Dist: numpydoc
